mapilli/__init__.py
mapilli/__main__.py
mapilli/client/__init__.py
mapilli/client/protocol.py
mapilli/client/session.py
mapilli/protocol/__init__.py
mapilli/protocol/constants.py
mapilli/protocol/request.py
mapilli/protocol/response.py
mapilli/py.typed
mapilli/utils/__init__.py
mapilli/utils/logging.py
mapilli-0.1.1.dist-info/WHEEL
mapilli-0.1.1.dist-info/entry_points.txt
mapilli-0.1.1.dist-info/METADATA
mapilli-0.1.1.dist-info/RECORD
