Metadata-Version: 2.3
Name: mapilli
Version: 0.1.1
Summary: Modern Python asyncio Finger protocol (RFC 1288) client library
Keywords: finger,protocol,client,asyncio,networking,rfc1288
Author: Alan Velasco
Author-email: Alan Velasco <alanvelasco.a@gmail.com>
License: MIT
Classifier: Development Status :: 3 - Alpha
Classifier: Intended Audience :: Developers
Classifier: License :: OSI Approved :: MIT License
Classifier: Programming Language :: Python :: 3
Classifier: Programming Language :: Python :: 3.10
Classifier: Programming Language :: Python :: 3.11
Classifier: Programming Language :: Python :: 3.12
Classifier: Programming Language :: Python :: 3.13
Classifier: Topic :: Internet
Classifier: Topic :: Software Development :: Libraries :: Python Modules
Classifier: Framework :: AsyncIO
Requires-Dist: rich>=13.0.0
Requires-Dist: structlog>=24.0.0
Requires-Dist: typer>=0.9.0
Requires-Python: >=3.10
Project-URL: Bug Tracker, https://github.com/alanbato/mapilli/issues
Project-URL: Documentation, https://mapilli.readthedocs.io
Project-URL: Repository, https://github.com/alanbato/mapilli
